crowsetta/__about__.py
crowsetta/__init__.py
crowsetta/annotation.py
crowsetta/bbox.py
crowsetta/segment.py
crowsetta/sequence.py
crowsetta/transcriber.py
crowsetta/typing.py
crowsetta/validation.py
crowsetta/examples/405_marron1_June_14_2016_69640887.audacity-description.txt
crowsetta/examples/405_marron1_June_14_2016_69640887.audacity.txt
crowsetta/examples/AVO-maea-basic.TextGrid
crowsetta/examples/AVO-maea-basic.TextGrid-description.txt
crowsetta/examples/Annotation.xml
crowsetta/examples/Annotation.xml-description.txt
crowsetta/examples/GO_24860x23748_ltr2_pup3_ch4_4800_m_337_295_fr1_p9_2021-10-02_12-35-01-description.txt
crowsetta/examples/GO_24860x23748_ltr2_pup3_ch4_4800_m_337_295_fr1_p9_2021-10-02_12-35-01.csv
crowsetta/examples/Recording_1_Segment_02.Table.1.selections-description.txt
crowsetta/examples/Recording_1_Segment_02.Table.1.selections.txt
crowsetta/examples/__init__.py
crowsetta/examples/_examples.py
crowsetta/examples/bird1.csv
crowsetta/examples/bird1.txt
crowsetta/examples/bl26lb16_190412_0721.20144_annotations-description.txt
crowsetta/examples/bl26lb16_190412_0721.20144_annotations.csv
crowsetta/examples/example-metadata.json
crowsetta/examples/gy6or6_baseline_230312_0808.138.cbin.not-description.txt
crowsetta/examples/gy6or6_baseline_230312_0808.138.cbin.not.mat
crowsetta/examples/sa1-description.txt
crowsetta/examples/sa1.phn
crowsetta/examples/spinetail-description.txt
crowsetta/examples/spinetail.txt
crowsetta/formats/__init__.py
crowsetta/formats/bbox/__init__.py
crowsetta/formats/bbox/audbbox.py
crowsetta/formats/bbox/raven.py
crowsetta/formats/seq/__init__.py
crowsetta/formats/seq/audseq.py
crowsetta/formats/seq/birdsongrec.py
crowsetta/formats/seq/generic.py
crowsetta/formats/seq/notmat.py
crowsetta/formats/seq/simple.py
crowsetta/formats/seq/timit.py
crowsetta/formats/seq/yarden.py
crowsetta/formats/seq/textgrid/__init__.py
crowsetta/formats/seq/textgrid/classes.py
crowsetta/formats/seq/textgrid/parse.py
crowsetta-5.1.3.post1.dist-info/licenses/LICENSE
crowsetta-5.1.3.post1.dist-info/WHEEL
crowsetta-5.1.3.post1.dist-info/METADATA
crowsetta-5.1.3.post1.dist-info/RECORD
