Metadata-Version: 2.4
Name: crowsetta
Version: 5.1.3.post1
Summary: A Python tool to work with any format for annotating animal sounds and bioacoustics data
Author-email: David Nicholson <nickledave@users.noreply.github.com>
Requires-Python: >=3.12
Classifier: License :: OSI Approved :: BSD License
Classifier: Development Status :: 5 - Production/Stable
Classifier: Programming Language :: Python
Classifier: Programming Language :: Python :: 3
Classifier: Programming Language :: Python :: 3.12
Classifier: Programming Language :: Python :: 3.13
Classifier: Programming Language :: Python :: 3.14
Classifier: Programming Language :: Python :: Implementation :: CPython
License-File: LICENSE
Requires-Dist: appdirs >=1.4.4
Requires-Dist: attrs >=25.3.0
Requires-Dist: numpy >=2.0.0
Requires-Dist: pandas >= 2.2.0
Requires-Dist: pandera >= 0.25.0
Requires-Dist: scipy >=1.12.0
Requires-Dist: SoundFile >=0.13.1
Project-URL: Documentation, https://crowsetta.readthedocs.io
Project-URL: Source, https://github.com/vocalpy/crowsetta
